[
  {
    "titel": "Pilates",
    "datum": "2026-02-27",
    "zeit": "08:00",
    "calendly": "https://calendly.com/funtasticfitnessurfahr/pilates"
  },
  {
    "titel": "Happy 30",
    "datum": "2026-02-27",
    "zeit": "10:00",
    "calendly": "https://calendly.com/funtasticfitnessurfahr/daily-30-urfahr"
  },
  {
    "titel": "Happy 30",
    "datum": "2026-02-27",
    "zeit": "12:00",
    "calendly": "https://calendly.com/funtasticfitnessurfahr/daily-30-urfahr"
  },
  {
    "titel": "Happy 30",
    "datum": "2026-02-27",
    "zeit": "16:00",
    "calendly": "https://calendly.com/funtasticfitnessurfahr/daily-30-urfahr"
  },
  {
    "titel": "Yoga",
    "datum": "2026-03-05",
    "zeit": "09:00",
    "calendly": "https://calendly.com/funtasticfitnessurfahr/yoga"
  },
  {
    "titel": "Yoga",
    "datum": "2026-03-12",
    "zeit": "09:00",
    "calendly": "https://calendly.com/funtasticfitnessurfahr/yoga"
  },
  {
    "titel": "Yoga",
    "datum": "2026-03-19",
    "zeit": "09:00",
    "calendly": "https://calendly.com/funtasticfitnessurfahr/yoga"
  },
  {
    "titel": "Yoga",
    "datum": "2026-03-26",
    "zeit": "09:00",
    "calendly": "https://calendly.com/funtasticfitnessurfahr/yoga"
  }
]